resources/config-example.yaml
resources/run-metrics-exporter.sh
resources/systemd/fsa-metrics.service
fsa_metrics/__init__.py
fsa_metrics/cli.py
fsa_metrics/collector.py
fsa_metrics/config.py
fsa_metrics/metrics.py
file_size_age_metrics-1.0.0.dist-info/LICENSE
file_size_age_metrics-1.0.0.dist-info/METADATA
file_size_age_metrics-1.0.0.dist-info/WHEEL
file_size_age_metrics-1.0.0.dist-info/entry_points.txt
file_size_age_metrics-1.0.0.dist-info/RECORD
