Metadata-Version: 2.3
Name: file-size-age-metrics
Version: 1.0.0
Summary: Metrics collector and exporter to monitor file sizes and ages.
License: GPL-3.0-or-later
Keywords: prometheus,metrics,file-metrics
Author: Niko Ehrenfeuchter
Author-email: nikolaus.ehrenfeuchter@unibas.ch
Requires-Python: >=3.8,<4.0
Classifier: License :: OSI Approved :: GNU General Public License v3 or later (GPLv3+)
Classifier: Programming Language :: Python :: 3
Classifier: Programming Language :: Python :: 3.8
Classifier: Programming Language :: Python :: 3.9
Classifier: Programming Language :: Python :: 3.10
Classifier: Programming Language :: Python :: 3.11
Classifier: Programming Language :: Python :: 3.12
Classifier: Programming Language :: Python :: 3.13
Requires-Dist: PyYAML (>=6.0,<7.0)
Requires-Dist: click (>=8.1.3,<9.0.0)
Requires-Dist: loguru (>=0.7.0,<0.8.0)
Requires-Dist: prometheus-client (>=0.21.1,<0.22.0)
Requires-Dist: python-box (>=7.2,<8.0)
Project-URL: Homepage, https://pypi.org/project/file-size-age-metrics/
Project-URL: Organisation Homepage, https://imcf.one/
Project-URL: Repository, https://github.com/imcf/file-size-age-metrics
